{
  "actionOverrides": [],
  "activateable": false,
  "childRelationships": [
    {
      "cascadeDelete": false,
      "childSObject": "FlowRecordRelation",
      "deprecatedAndHidden": false,
      "field": "RelatedRecordId",
      "junctionIdListNames": [],
      "junctionReferenceTo": [],
      "relationshipName": null,
      "restrictedDelete": false
    }
  ],
  "compactLayoutable": false,
  "createable": true,
  "custom": false,
  "customSetting": false,
  "deletable": true,
  "deprecatedAndHidden": false,
  "feedEnabled": false,
  "fields": [
    {
      "aggregatable": true,
      "aiPredictionField": false,
      "autoNumber": false,
      "byteLength": 18,
      "calculated": false,
      "calculatedFormula": null,
      "cascadeDelete": false,
      "caseSensitive": false,
      "compoundFieldName": null,
      "controllerName": null,
      "createable": false,
      "custom": false,
      "defaultValue": null,
      "defaultValueFormula": null,
      "defaultedOnCreate": true,
      "dependentPicklist": false,
      "deprecatedAndHidden": false,
      "digits": 0,
      "displayLocationInDecimal": false,
      "encrypted": false,
      "externalId": false,
      "extraTypeInfo": null,
      "filterable": true,
      "filteredLookupInfo": null,
      "formulaTreatNullNumberAsZero": false,
      "groupable": true,
      "highScaleNumber": false,
      "htmlFormatted": false,
      "idLookup": true,
      "inlineHelpText": null,
      "label": "Quote PDF ID",
      "length": 18,
      "mask": null,
      "maskType": null,
      "name": "Id",
      "nameField": false,
      "namePointing": false,
      "nillable": false,
      "permissionable": false,
      "picklistValues": [],
      "polymorphicForeignKey": false,
      "precision": 0,
      "queryByDistance": false,
      "referenceTargetField": null,
      "referenceTo": [],
      "relationshipName": null,
      "relationshipOrder": null,
      "restrictedDelete": false,
      "restrictedPicklist": false,
      "scale": 0,
      "searchPrefilterable": false,
      "soapType": "tns:ID",
      "sortable": true,
      "type": "id",
      "unique": false,
      "updateable": false,
      "writeRequiresMasterRead": false
    },
    {
      "aggregatable": true,
      "aiPredictionField": false,
      "autoNumber": false,
      "byteLength": 810,
      "calculated": false,
      "calculatedFormula": null,
      "cascadeDelete": false,
      "caseSensitive": false,
      "compoundFieldName": null,
      "controllerName": null,
      "createable": false,
      "custom": false,
      "defaultValue": null,
      "defaultValueFormula": null,
      "defaultedOnCreate": false,
      "dependentPicklist": false,
      "deprecatedAndHidden": false,
      "digits": 0,
      "displayLocationInDecimal": false,
      "encrypted": false,
      "externalId": false,
      "extraTypeInfo": null,
      "filterable": true,
      "filteredLookupInfo": null,
      "formulaTreatNullNumberAsZero": false,
      "groupable": false,
      "highScaleNumber": false,
      "htmlFormatted": false,
      "idLookup": true,
      "inlineHelpText": null,
      "label": "Name",
      "length": 270,
      "mask": null,
      "maskType": null,
      "name": "Name",
      "nameField": true,
      "namePointing": false,
      "nillable": false,
      "permissionable": false,
      "picklistValues": [],
      "polymorphicForeignKey": false,
      "precision": 0,
      "queryByDistance": false,
      "referenceTargetField": null,
      "referenceTo": [],
      "relationshipName": null,
      "relationshipOrder": null,
      "restrictedDelete": false,
      "restrictedPicklist": false,
      "scale": 0,
      "searchPrefilterable": false,
      "soapType": "xsd:string",
      "sortable": true,
      "type": "string",
      "unique": false,
      "updateable": false,
      "writeRequiresMasterRead": false
    },
    {
      "aggregatable": true,
      "aiPredictionField": false,
      "autoNumber": false,
      "byteLength": 18,
      "calculated": false,
      "calculatedFormula": null,
      "cascadeDelete": false,
      "caseSensitive": false,
      "compoundFieldName": null,
      "controllerName": null,
      "createable": true,
      "custom": false,
      "defaultValue": null,
      "defaultValueFormula": null,
      "defaultedOnCreate": false,
      "dependentPicklist": false,
      "deprecatedAndHidden": false,
      "digits": 0,
      "displayLocationInDecimal": false,
      "encrypted": false,
      "externalId": false,
      "extraTypeInfo": null,
      "filterable": true,
      "filteredLookupInfo": null,
      "formulaTreatNullNumberAsZero": false,
      "groupable": true,
      "highScaleNumber": false,
      "htmlFormatted": false,
      "idLookup": false,
      "inlineHelpText": null,
      "label": "Quote ID",
      "length": 18,
      "mask": null,
      "maskType": null,
      "name": "QuoteId",
      "nameField": false,
      "namePointing": false,
      "nillable": false,
      "permissionable": false,
      "picklistValues": [],
      "polymorphicForeignKey": false,
      "precision": 0,
      "queryByDistance": false,
      "referenceTargetField": null,
      "referenceTo": [
        "Quote"
      ],
      "relationshipName": "Quote",
      "relationshipOrder": null,
      "restrictedDelete": false,
      "restrictedPicklist": false,
      "scale": 0,
      "searchPrefilterable": false,
      "soapType": "tns:ID",
      "sortable": true,
      "type": "reference",
      "unique": false,
      "updateable": false,
      "writeRequiresMasterRead": false
    },
    {
      "aggregatable": true,
      "aiPredictionField": false,
      "autoNumber": false,
      "byteLength": 18,
      "calculated": false,
      "calculatedFormula": null,
      "cascadeDelete": false,
      "caseSensitive": false,
      "compoundFieldName": null,
      "controllerName": null,
      "createable": true,
      "custom": false,
      "defaultValue": null,
      "defaultValueFormula": null,
      "defaultedOnCreate": false,
      "dependentPicklist": false,
      "deprecatedAndHidden": false,
      "digits": 0,
      "displayLocationInDecimal": false,
      "encrypted": false,
      "externalId": false,
      "extraTypeInfo": null,
      "filterable": true,
      "filteredLookupInfo": null,
      "formulaTreatNullNumberAsZero": false,
      "groupable": true,
      "highScaleNumber": false,
      "htmlFormatted": false,
      "idLookup": false,
      "inlineHelpText": null,
      "label": "ContentVersion ID",
      "length": 18,
      "mask": null,
      "maskType": null,
      "name": "ContentVersionDocumentId",
      "nameField": false,
      "namePointing": false,
      "nillable": false,
      "permissionable": false,
      "picklistValues": [],
      "polymorphicForeignKey": false,
      "precision": 0,
      "queryByDistance": false,
      "referenceTargetField": null,
      "referenceTo": [
        "ContentVersion"
      ],
      "relationshipName": null,
      "relationshipOrder": null,
      "restrictedDelete": false,
      "restrictedPicklist": false,
      "scale": 0,
      "searchPrefilterable": false,
      "soapType": "tns:ID",
      "sortable": true,
      "type": "reference",
      "unique": false,
      "updateable": false,
      "writeRequiresMasterRead": false
    },
    {
      "aggregatable": false,
      "aiPredictionField": false,
      "autoNumber": false,
      "byteLength": 0,
      "calculated": false,
      "calculatedFormula": null,
      "cascadeDelete": false,
      "caseSensitive": false,
      "compoundFieldName": null,
      "controllerName": null,
      "createable": true,
      "custom": false,
      "defaultValue": null,
      "defaultValueFormula": null,
      "defaultedOnCreate": false,
      "dependentPicklist": false,
      "deprecatedAndHidden": false,
      "digits": 0,
      "displayLocationInDecimal": false,
      "encrypted": false,
      "externalId": false,
      "extraTypeInfo": null,
      "filterable": false,
      "filteredLookupInfo": null,
      "formulaTreatNullNumberAsZero": false,
      "groupable": false,
      "highScaleNumber": false,
      "htmlFormatted": false,
      "idLookup": false,
      "inlineHelpText": null,
      "label": "PDF Document",
      "length": 0,
      "mask": null,
      "maskType": null,
      "name": "Document",
      "nameField": false,
      "namePointing": false,
      "nillable": true,
      "permissionable": false,
      "picklistValues": [],
      "polymorphicForeignKey": false,
      "precision": 0,
      "queryByDistance": false,
      "referenceTargetField": null,
      "referenceTo": [],
      "relationshipName": null,
      "relationshipOrder": null,
      "restrictedDelete": false,
      "restrictedPicklist": false,
      "scale": 0,
      "searchPrefilterable": false,
      "soapType": "xsd:base64Binary",
      "sortable": false,
      "type": "base64",
      "unique": false,
      "updateable": false,
      "writeRequiresMasterRead": false
    },
    {
      "aggregatable": true,
      "aiPredictionField": false,
      "autoNumber": false,
      "byteLength": 0,
      "calculated": false,
      "calculatedFormula": null,
      "cascadeDelete": false,
      "caseSensitive": false,
      "compoundFieldName": null,
      "controllerName": null,
      "createable": false,
      "custom": false,
      "defaultValue": null,
      "defaultValueFormula": null,
      "defaultedOnCreate": false,
      "dependentPicklist": false,
      "deprecatedAndHidden": false,
      "digits": 0,
      "displayLocationInDecimal": false,
      "encrypted": false,
      "externalId": false,
      "extraTypeInfo": null,
      "filterable": true,
      "filteredLookupInfo": null,
      "formulaTreatNullNumberAsZero": false,
      "groupable": false,
      "highScaleNumber": false,
      "htmlFormatted": false,
      "idLookup": false,
      "inlineHelpText": null,
      "label": "Grand Total",
      "length": 0,
      "mask": null,
      "maskType": null,
      "name": "GrandTotal",
      "nameField": false,
      "namePointing": false,
      "nillable": true,
      "permissionable": false,
      "picklistValues": [],
      "polymorphicForeignKey": false,
      "precision": 18,
      "queryByDistance": false,
      "referenceTargetField": null,
      "referenceTo": [],
      "relationshipName": null,
      "relationshipOrder": null,
      "restrictedDelete": false,
      "restrictedPicklist": false,
      "scale": 2,
      "searchPrefilterable": false,
      "soapType": "xsd:double",
      "sortable": true,
      "type": "currency",
      "unique": false,
      "updateable": false,
      "writeRequiresMasterRead": false
    },
    {
      "aggregatable": true,
      "aiPredictionField": false,
      "autoNumber": false,
      "byteLength": 0,
      "calculated": false,
      "calculatedFormula": null,
      "cascadeDelete": false,
      "caseSensitive": false,
      "compoundFieldName": null,
      "controllerName": null,
      "createable": false,
      "custom": false,
      "defaultValue": null,
      "defaultValueFormula": null,
      "defaultedOnCreate": false,
      "dependentPicklist": false,
      "deprecatedAndHidden": false,
      "digits": 0,
      "displayLocationInDecimal": false,
      "encrypted": false,
      "externalId": false,
      "extraTypeInfo": null,
      "filterable": true,
      "filteredLookupInfo": null,
      "formulaTreatNullNumberAsZero": false,
      "groupable": false,
      "highScaleNumber": false,
      "htmlFormatted": false,
      "idLookup": false,
      "inlineHelpText": null,
      "label": "Discount",
      "length": 0,
      "mask": null,
      "maskType": null,
      "name": "Discount",
      "nameField": false,
      "namePointing": false,
      "nillable": true,
      "permissionable": false,
      "picklistValues": [],
      "polymorphicForeignKey": false,
      "precision": 5,
      "queryByDistance": false,
      "referenceTargetField": null,
      "referenceTo": [],
      "relationshipName": null,
      "relationshipOrder": null,
      "restrictedDelete": false,
      "restrictedPicklist": false,
      "scale": 2,
      "searchPrefilterable": false,
      "soapType": "xsd:double",
      "sortable": true,
      "type": "percent",
      "unique": false,
      "updateable": false,
      "writeRequiresMasterRead": false
    },
    {
      "aggregatable": false,
      "aiPredictionField": false,
      "autoNumber": false,
      "byteLength": 0,
      "calculated": false,
      "calculatedFormula": null,
      "cascadeDelete": false,
      "caseSensitive": false,
      "compoundFieldName": null,
      "controllerName": null,
      "createable": false,
      "custom": false,
      "defaultValue": false,
      "defaultValueFormula": null,
      "defaultedOnCreate": true,
      "dependentPicklist": false,
      "deprecatedAndHidden": false,
      "digits": 0,
      "displayLocationInDecimal": false,
      "encrypted": false,
      "externalId": false,
      "extraTypeInfo": null,
      "filterable": true,
      "filteredLookupInfo": null,
      "formulaTreatNullNumberAsZero": false,
      "groupable": true,
      "highScaleNumber": false,
      "htmlFormatted": false,
      "idLookup": false,
      "inlineHelpText": null,
      "label": "Deleted",
      "length": 0,
      "mask": null,
      "maskType": null,
      "name": "IsDeleted",
      "nameField": false,
      "namePointing": false,
      "nillable": false,
      "permissionable": false,
      "picklistValues": [],
      "polymorphicForeignKey": false,
      "precision": 0,
      "queryByDistance": false,
      "referenceTargetField": null,
      "referenceTo": [],
      "relationshipName": null,
      "relationshipOrder": null,
      "restrictedDelete": false,
      "restrictedPicklist": false,
      "scale": 0,
      "searchPrefilterable": false,
      "soapType": "xsd:boolean",
      "sortable": true,
      "type": "boolean",
      "unique": false,
      "updateable": false,
      "writeRequiresMasterRead": false
    },
    {
      "aggregatable": true,
      "aiPredictionField": false,
      "autoNumber": false,
      "byteLength": 0,
      "calculated": false,
      "calculatedFormula": null,
      "cascadeDelete": false,
      "caseSensitive": false,
      "compoundFieldName": null,
      "controllerName": null,
      "createable": false,
      "custom": false,
      "defaultValue": null,
      "defaultValueFormula": null,
      "defaultedOnCreate": true,
      "dependentPicklist": false,
      "deprecatedAndHidden": false,
      "digits": 0,
      "displayLocationInDecimal": false,
      "encrypted": false,
      "externalId": false,
      "extraTypeInfo": null,
      "filterable": true,
      "filteredLookupInfo": null,
      "formulaTreatNullNumberAsZero": false,
      "groupable": false,
      "highScaleNumber": false,
      "htmlFormatted": false,
      "idLookup": false,
      "inlineHelpText": null,
      "label": "Created Date",
      "length": 0,
      "mask": null,
      "maskType": null,
      "name": "CreatedDate",
      "nameField": false,
      "namePointing": false,
      "nillable": false,
      "permissionable": false,
      "picklistValues": [],
      "polymorphicForeignKey": false,
      "precision": 0,
      "queryByDistance": false,
      "referenceTargetField": null,
      "referenceTo": [],
      "relationshipName": null,
      "relationshipOrder": null,
      "restrictedDelete": false,
      "restrictedPicklist": false,
      "scale": 0,
      "searchPrefilterable": false,
      "soapType": "xsd:dateTime",
      "sortable": true,
      "type": "datetime",
      "unique": false,
      "updateable": false,
      "writeRequiresMasterRead": false
    },
    {
      "aggregatable": true,
      "aiPredictionField": false,
      "autoNumber": false,
      "byteLength": 18,
      "calculated": false,
      "calculatedFormula": null,
      "cascadeDelete": false,
      "caseSensitive": false,
      "compoundFieldName": null,
      "controllerName": null,
      "createable": false,
      "custom": false,
      "defaultValue": null,
      "defaultValueFormula": null,
      "defaultedOnCreate": true,
      "dependentPicklist": false,
      "deprecatedAndHidden": false,
      "digits": 0,
      "displayLocationInDecimal": false,
      "encrypted": false,
      "externalId": false,
      "extraTypeInfo": null,
      "filterable": true,
      "filteredLookupInfo": null,
      "formulaTreatNullNumberAsZero": false,
      "groupable": true,
      "highScaleNumber": false,
      "htmlFormatted": false,
      "idLookup": false,
      "inlineHelpText": null,
      "label": "Created By ID",
      "length": 18,
      "mask": null,
      "maskType": null,
      "name": "CreatedById",
      "nameField": false,
      "namePointing": false,
      "nillable": false,
      "permissionable": false,
      "picklistValues": [],
      "polymorphicForeignKey": false,
      "precision": 0,
      "queryByDistance": false,
      "referenceTargetField": null,
      "referenceTo": [
        "User"
      ],
      "relationshipName": "CreatedBy",
      "relationshipOrder": null,
      "restrictedDelete": false,
      "restrictedPicklist": false,
      "scale": 0,
      "searchPrefilterable": false,
      "soapType": "tns:ID",
      "sortable": true,
      "type": "reference",
      "unique": false,
      "updateable": false,
      "writeRequiresMasterRead": false
    },
    {
      "aggregatable": true,
      "aiPredictionField": false,
      "autoNumber": false,
      "byteLength": 0,
      "calculated": false,
      "calculatedFormula": null,
      "cascadeDelete": false,
      "caseSensitive": false,
      "compoundFieldName": null,
      "controllerName": null,
      "createable": false,
      "custom": false,
      "defaultValue": null,
      "defaultValueFormula": null,
      "defaultedOnCreate": true,
      "dependentPicklist": false,
      "deprecatedAndHidden": false,
      "digits": 0,
      "displayLocationInDecimal": false,
      "encrypted": false,
      "externalId": false,
      "extraTypeInfo": null,
      "filterable": true,
      "filteredLookupInfo": null,
      "formulaTreatNullNumberAsZero": false,
      "groupable": false,
      "highScaleNumber": false,
      "htmlFormatted": false,
      "idLookup": false,
      "inlineHelpText": null,
      "label": "Last Modified Date",
      "length": 0,
      "mask": null,
      "maskType": null,
      "name": "LastModifiedDate",
      "nameField": false,
      "namePointing": false,
      "nillable": false,
      "permissionable": false,
      "picklistValues": [],
      "polymorphicForeignKey": false,
      "precision": 0,
      "queryByDistance": false,
      "referenceTargetField": null,
      "referenceTo": [],
      "relationshipName": null,
      "relationshipOrder": null,
      "restrictedDelete": false,
      "restrictedPicklist": false,
      "scale": 0,
      "searchPrefilterable": false,
      "soapType": "xsd:dateTime",
      "sortable": true,
      "type": "datetime",
      "unique": false,
      "updateable": false,
      "writeRequiresMasterRead": false
    },
    {
      "aggregatable": true,
      "aiPredictionField": false,
      "autoNumber": false,
      "byteLength": 18,
      "calculated": false,
      "calculatedFormula": null,
      "cascadeDelete": false,
      "caseSensitive": false,
      "compoundFieldName": null,
      "controllerName": null,
      "createable": false,
      "custom": false,
      "defaultValue": null,
      "defaultValueFormula": null,
      "defaultedOnCreate": true,
      "dependentPicklist": false,
      "deprecatedAndHidden": false,
      "digits": 0,
      "displayLocationInDecimal": false,
      "encrypted": false,
      "externalId": false,
      "extraTypeInfo": null,
      "filterable": true,
      "filteredLookupInfo": null,
      "formulaTreatNullNumberAsZero": false,
      "groupable": true,
      "highScaleNumber": false,
      "htmlFormatted": false,
      "idLookup": false,
      "inlineHelpText": null,
      "label": "Last Modified By ID",
      "length": 18,
      "mask": null,
      "maskType": null,
      "name": "LastModifiedById",
      "nameField": false,
      "namePointing": false,
      "nillable": false,
      "permissionable": false,
      "picklistValues": [],
      "polymorphicForeignKey": false,
      "precision": 0,
      "queryByDistance": false,
      "referenceTargetField": null,
      "referenceTo": [
        "User"
      ],
      "relationshipName": "LastModifiedBy",
      "relationshipOrder": null,
      "restrictedDelete": false,
      "restrictedPicklist": false,
      "scale": 0,
      "searchPrefilterable": false,
      "soapType": "tns:ID",
      "sortable": true,
      "type": "reference",
      "unique": false,
      "updateable": false,
      "writeRequiresMasterRead": false
    },
    {
      "aggregatable": true,
      "aiPredictionField": false,
      "autoNumber": false,
      "byteLength": 0,
      "calculated": false,
      "calculatedFormula": null,
      "cascadeDelete": false,
      "caseSensitive": false,
      "compoundFieldName": null,
      "controllerName": null,
      "createable": false,
      "custom": false,
      "defaultValue": null,
      "defaultValueFormula": null,
      "defaultedOnCreate": true,
      "dependentPicklist": false,
      "deprecatedAndHidden": false,
      "digits": 0,
      "displayLocationInDecimal": false,
      "encrypted": false,
      "externalId": false,
      "extraTypeInfo": null,
      "filterable": true,
      "filteredLookupInfo": null,
      "formulaTreatNullNumberAsZero": false,
      "groupable": false,
      "highScaleNumber": false,
      "htmlFormatted": false,
      "idLookup": false,
      "inlineHelpText": null,
      "label": "System Modstamp",
      "length": 0,
      "mask": null,
      "maskType": null,
      "name": "SystemModstamp",
      "nameField": false,
      "namePointing": false,
      "nillable": false,
      "permissionable": false,
      "picklistValues": [],
      "polymorphicForeignKey": false,
      "precision": 0,
      "queryByDistance": false,
      "referenceTargetField": null,
      "referenceTo": [],
      "relationshipName": null,
      "relationshipOrder": null,
      "restrictedDelete": false,
      "restrictedPicklist": false,
      "scale": 0,
      "searchPrefilterable": false,
      "soapType": "xsd:dateTime",
      "sortable": true,
      "type": "datetime",
      "unique": false,
      "updateable": false,
      "writeRequiresMasterRead": false
    }
  ],
  "hasSubtypes": false,
  "isSubtype": false,
  "keyPrefix": "0QD",
  "label": "Quote PDF",
  "labelPlural": "Quote PDFs",
  "layoutable": false,
  "listviewable": null,
  "lookupLayoutable": null,
  "mergeable": false,
  "mruEnabled": false,
  "name": "QuoteDocument",
  "namedLayoutInfos": [],
  "networkScopeFieldName": null,
  "queryable": true,
  "recordTypeInfos": [],
  "replicateable": true,
  "retrieveable": true,
  "searchLayoutable": false,
  "searchable": false,
  "supportedScopes": [
    {
      "label": "All quote pdfs",
      "name": "everything"
    }
  ],
  "triggerable": false,
  "undeletable": true,
  "updateable": false,
  "urls": {
    "rowTemplate": "/services/data/v43.0/sobjects/QuoteDocument/{ID}",
    "defaultValues": "/services/data/v43.0/sobjects/QuoteDocument/defaultValues?recordTypeId&fields",
    "describe": "/services/data/v43.0/sobjects/QuoteDocument/describe",
    "sobject": "/services/data/v43.0/sobjects/QuoteDocument"
  }
}